abstractions/__init__.py
abstractions/bigquery.py
abstractions/datastore.py
abstractions/pubsub.py
enums/__init__.py
enums/status_enum.py
needle_forms-0.0.5.dist-info/LICENCE
needle_forms-0.0.5.dist-info/METADATA
needle_forms-0.0.5.dist-info/WHEEL
needle_forms-0.0.5.dist-info/top_level.txt
needle_forms-0.0.5.dist-info/RECORD
